AaioAPI/AaioAPI.py
AaioAPI/AsyncAaioAPI.py
AaioAPI/__init__.py
AaioAPI-2.5.6.dist-info/LICENSE
AaioAPI-2.5.6.dist-info/METADATA
AaioAPI-2.5.6.dist-info/WHEEL
AaioAPI-2.5.6.dist-info/top_level.txt
AaioAPI-2.5.6.dist-info/RECORD
