Metadata-Version: 2.1
Name: AaioAPI
Version: 2.5.6
Summary: The best, convenient and simple library for connecting Aaio payment
Home-page: https://github.com/wkillus/AaioAPI
Author: Fre4ka
Author-email: yusufbek0303@gmail.com
Project-URL: Homepage, https://github.com/wkillus/AaioAPI
Project-URL: Documentation, https://wiki.aaio.so/
Keywords: aaio api python payments aaio-api aaioapi
Classifier: Programming Language :: Python :: 3.11
Classifier: License :: OSI Approved :: MIT License
Classifier: Operating System :: OS Independent
Requires-Python: >=3.7
License-File: LICENSE
